[{"timestamp":"2025-10-27T01:38:22.332Z","count":0,"uniques":0},{"timestamp":"2025-10-28T01:21:30.743Z","count":0,"uniques":0},{"timestamp":"2025-10-29T01:26:56.873Z","count":0,"uniques":0},{"timestamp":"2025-10-30T01:26:26.487Z","count":0,"uniques":0},{"timestamp":"2025-10-31T01:23:47.228Z","count":0,"uniques":0},{"timestamp":"2025-11-01T01:28:04.650Z","count":0,"uniques":0},{"timestamp":"2025-11-02T01:28:52.162Z","count":0,"uniques":0},{"timestamp":"2025-11-03T01:27:31.428Z","count":0,"uniques":0},{"timestamp":"2025-11-04T01:24:40.691Z","count":0,"uniques":0},{"timestamp":"2025-11-05T01:25:41.901Z","count":0,"uniques":0},{"timestamp":"2025-11-06T01:25:19.081Z","count":0,"uniques":0},{"timestamp":"2025-11-07T01:24:56.377Z","count":0,"uniques":0},{"timestamp":"2025-11-08T01:20:32.132Z","count":0,"uniques":0},{"timestamp":"2025-11-09T01:28:19.408Z","count":0,"uniques":0},{"timestamp":"2025-11-10T01:28:18.048Z","count":0,"uniques":0},{"timestamp":"2025-11-11T01:25:46.182Z","count":0,"uniques":0},{"timestamp":"2025-11-12T01:25:22.415Z","count":0,"uniques":0},{"timestamp":"2025-11-13T01:26:13.917Z","count":0,"uniques":0},{"timestamp":"2025-11-14T01:25:58.831Z","count":0,"uniques":0},{"timestamp":"2025-11-15T01:23:02.475Z","count":0,"uniques":0},{"timestamp":"2025-11-16T01:38:05.546Z","count":0,"uniques":0},{"timestamp":"2025-11-17T01:26:12.935Z","count":0,"uniques":0},{"timestamp":"2025-11-18T01:25:09.790Z","count":0,"uniques":0},{"timestamp":"2025-11-19T01:24:54.057Z","count":0,"uniques":0},{"timestamp":"2025-11-20T01:23:40.822Z","count":0,"uniques":0},{"timestamp":"2025-11-21T01:24:22.661Z","count":0,"uniques":0},{"timestamp":"2025-11-22T01:21:47.482Z","count":0,"uniques":0},{"timestamp":"2025-11-23T01:44:34.364Z","count":0,"uniques":0},{"timestamp":"2025-11-24T01:39:46.501Z","count":0,"uniques":0},{"timestamp":"2025-11-25T01:25:41.560Z","count":0,"uniques":0},{"timestamp":"2025-11-26T01:25:38.143Z","count":0,"uniques":0}]
