[{"timestamp":"2025-04-20T01:30:01.902Z","count":0,"uniques":0},{"timestamp":"2025-04-21T01:28:49.449Z","count":0,"uniques":0},{"timestamp":"2025-04-22T01:25:11.070Z","count":0,"uniques":0},{"timestamp":"2025-04-23T01:25:43.176Z","count":0,"uniques":0},{"timestamp":"2025-04-24T01:25:49.558Z","count":0,"uniques":0},{"timestamp":"2025-04-25T01:26:36.125Z","count":0,"uniques":0},{"timestamp":"2025-04-26T01:23:13.609Z","count":0,"uniques":0},{"timestamp":"2025-04-27T01:30:37.768Z","count":0,"uniques":0},{"timestamp":"2025-04-28T01:28:02.450Z","count":0,"uniques":0},{"timestamp":"2025-04-29T01:26:28.873Z","count":0,"uniques":0},{"timestamp":"2025-04-30T01:26:17.492Z","count":0,"uniques":0},{"timestamp":"2025-05-01T01:41:42.656Z","count":0,"uniques":0},{"timestamp":"2025-05-02T01:26:31.080Z","count":0,"uniques":0},{"timestamp":"2025-05-03T01:24:47.677Z","count":0,"uniques":0},{"timestamp":"2025-05-04T01:42:22.143Z","count":0,"uniques":0},{"timestamp":"2025-05-05T01:29:51.364Z","count":0,"uniques":0},{"timestamp":"2025-05-06T01:27:04.157Z","count":0,"uniques":0},{"timestamp":"2025-05-07T01:28:09.579Z","count":0,"uniques":0},{"timestamp":"2025-05-08T01:28:00.593Z","count":0,"uniques":0},{"timestamp":"2025-05-09T01:27:19.398Z","count":0,"uniques":0},{"timestamp":"2025-05-10T01:24:47.236Z","count":0,"uniques":0},{"timestamp":"2025-05-11T01:40:28.009Z","count":0,"uniques":0},{"timestamp":"2025-05-12T01:30:59.455Z","count":0,"uniques":0},{"timestamp":"2025-05-13T01:29:11.944Z","count":0,"uniques":0},{"timestamp":"2025-05-14T01:27:27.960Z","count":0,"uniques":0},{"timestamp":"2025-05-15T01:25:45.621Z","count":0,"uniques":0},{"timestamp":"2025-05-16T01:29:08.111Z","count":0,"uniques":0},{"timestamp":"2025-05-17T01:26:47.978Z","count":0,"uniques":0},{"timestamp":"2025-05-18T01:41:23.574Z","count":0,"uniques":0},{"timestamp":"2025-05-19T01:40:57.001Z","count":0,"uniques":0},{"timestamp":"2025-05-20T01:29:25.477Z","count":0,"uniques":0}]
