[{"timestamp":"2026-02-19T02:08:36.426Z","count":0,"uniques":0},{"timestamp":"2026-02-20T02:04:28.452Z","count":0,"uniques":0},{"timestamp":"2026-02-21T01:59:16.601Z","count":0,"uniques":0},{"timestamp":"2026-02-22T02:08:26.345Z","count":0,"uniques":0},{"timestamp":"2026-02-23T02:09:05.301Z","count":0,"uniques":0},{"timestamp":"2026-02-24T02:05:40.906Z","count":0,"uniques":0},{"timestamp":"2026-02-25T02:08:03.805Z","count":0,"uniques":0},{"timestamp":"2026-02-26T02:03:47.871Z","count":0,"uniques":0}]
