[{"timestamp":"2026-02-08T02:31:54.422Z","count":0,"uniques":0},{"timestamp":"2026-02-09T02:10:08.769Z","count":0,"uniques":0},{"timestamp":"2026-02-10T05:53:15.776Z","count":0,"uniques":0},{"timestamp":"2026-02-11T02:15:56.075Z","count":0,"uniques":0},{"timestamp":"2026-02-12T02:09:51.092Z","count":0,"uniques":0},{"timestamp":"2026-02-13T02:12:25.319Z","count":0,"uniques":0},{"timestamp":"2026-02-14T02:01:02.170Z","count":0,"uniques":0},{"timestamp":"2026-02-15T02:11:55.085Z","count":0,"uniques":0}]
