[{"timestamp":"2026-06-21T04:13:40.827Z","count":0,"uniques":0},{"timestamp":"2026-06-22T04:13:33.842Z","count":0,"uniques":0},{"timestamp":"2026-06-23T03:33:43.480Z","count":0,"uniques":0},{"timestamp":"2026-06-24T03:36:45.694Z","count":0,"uniques":0},{"timestamp":"2026-06-25T03:34:22.063Z","count":0,"uniques":0},{"timestamp":"2026-06-26T03:42:46.514Z","count":0,"uniques":0},{"timestamp":"2026-06-27T03:04:31.305Z","count":0,"uniques":0},{"timestamp":"2026-06-28T03:47:38.414Z","count":0,"uniques":0}]
