[{"timestamp":"2026-03-11T02:04:07.944Z","count":0,"uniques":0},{"timestamp":"2026-03-12T02:10:23.371Z","count":0,"uniques":0},{"timestamp":"2026-03-13T06:59:35.319Z","count":0,"uniques":0},{"timestamp":"2026-03-14T02:05:18.397Z","count":0,"uniques":0},{"timestamp":"2026-03-15T02:29:05.237Z","count":0,"uniques":0},{"timestamp":"2026-03-16T02:31:16.069Z","count":0,"uniques":0},{"timestamp":"2026-03-17T02:10:03.846Z","count":0,"uniques":0},{"timestamp":"2026-03-18T02:14:11.740Z","count":0,"uniques":0}]
