[{"timestamp":"2025-08-21T01:28:06.666Z","count":0,"uniques":0},{"timestamp":"2025-08-22T01:28:53.657Z","count":0,"uniques":0},{"timestamp":"2025-08-23T01:26:03.063Z","count":0,"uniques":0},{"timestamp":"2025-08-24T01:45:30.999Z","count":0,"uniques":0},{"timestamp":"2025-08-25T01:31:49.538Z","count":0,"uniques":0},{"timestamp":"2025-08-26T01:29:59.515Z","count":0,"uniques":0},{"timestamp":"2025-08-27T01:27:45.011Z","count":0,"uniques":0},{"timestamp":"2025-08-28T01:26:58.575Z","count":0,"uniques":0}]
