[{"timestamp":"2026-03-17T02:09:43.351Z","count":0,"uniques":0},{"timestamp":"2026-03-18T02:13:50.476Z","count":0,"uniques":0},{"timestamp":"2026-03-19T02:14:54.963Z","count":0,"uniques":0},{"timestamp":"2026-03-20T02:09:07.966Z","count":0,"uniques":0},{"timestamp":"2026-03-21T02:03:17.298Z","count":0,"uniques":0},{"timestamp":"2026-03-22T02:15:39.802Z","count":0,"uniques":0},{"timestamp":"2026-03-23T02:15:46.544Z","count":0,"uniques":0},{"timestamp":"2026-03-24T02:07:59.003Z","count":0,"uniques":0}]
