[{"timestamp":"2025-08-24T01:40:04.416Z","count":0,"uniques":0},{"timestamp":"2025-08-25T01:26:41.527Z","count":0,"uniques":0},{"timestamp":"2025-08-26T01:24:31.270Z","count":0,"uniques":0},{"timestamp":"2025-08-27T01:22:09.369Z","count":0,"uniques":0},{"timestamp":"2025-08-28T01:21:24.549Z","count":0,"uniques":0},{"timestamp":"2025-08-29T01:21:39.516Z","count":0,"uniques":0},{"timestamp":"2025-08-30T01:17:40.063Z","count":0,"uniques":0},{"timestamp":"2025-08-31T01:26:15.953Z","count":0,"uniques":0}]
