[{"timestamp":"2026-06-16T04:04:43.708Z","count":0,"uniques":0},{"timestamp":"2026-06-17T04:06:05.436Z","count":0,"uniques":0},{"timestamp":"2026-06-18T03:57:55.509Z","count":0,"uniques":0},{"timestamp":"2026-06-19T04:18:07.164Z","count":0,"uniques":0},{"timestamp":"2026-06-20T03:39:50.655Z","count":0,"uniques":0},{"timestamp":"2026-06-21T00:00:00.000Z","count":4,"uniques":1},{"timestamp":"2026-06-22T04:11:51.938Z","count":0,"uniques":0},{"timestamp":"2026-06-23T03:32:21.441Z","count":0,"uniques":0}]
