[{"timestamp":"2026-07-17T02:33:33.278Z","count":0,"uniques":0},{"timestamp":"2026-07-18T02:24:11.274Z","count":0,"uniques":0},{"timestamp":"2026-07-19T02:36:54.046Z","count":0,"uniques":0},{"timestamp":"2026-07-20T02:51:45.833Z","count":0,"uniques":0},{"timestamp":"2026-07-21T02:34:43.021Z","count":0,"uniques":0},{"timestamp":"2026-07-22T02:34:08.355Z","count":0,"uniques":0},{"timestamp":"2026-07-23T02:38:20.987Z","count":0,"uniques":0},{"timestamp":"2026-07-24T02:35:03.379Z","count":0,"uniques":0}]
