[{"timestamp":"2026-01-15T01:43:12.470Z","count":0,"uniques":0},{"timestamp":"2026-01-16T01:44:49.931Z","count":0,"uniques":0},{"timestamp":"2026-01-17T01:39:49.282Z","count":0,"uniques":0},{"timestamp":"2026-01-18T01:51:07.934Z","count":0,"uniques":0},{"timestamp":"2026-01-19T01:49:41.918Z","count":0,"uniques":0},{"timestamp":"2026-01-20T01:44:45.175Z","count":0,"uniques":0},{"timestamp":"2026-01-21T01:47:26.431Z","count":0,"uniques":0},{"timestamp":"2026-01-22T01:47:27.903Z","count":0,"uniques":0}]
