[{"timestamp":"2025-07-08T01:38:16.676Z","count":0,"uniques":0},{"timestamp":"2025-07-09T01:39:22.505Z","count":0,"uniques":0},{"timestamp":"2025-07-10T01:39:29.749Z","count":0,"uniques":0},{"timestamp":"2025-07-11T01:40:52.245Z","count":0,"uniques":0},{"timestamp":"2025-07-12T01:41:51.593Z","count":0,"uniques":0},{"timestamp":"2025-07-13T01:49:08.212Z","count":0,"uniques":0},{"timestamp":"2025-07-14T01:45:08.784Z","count":0,"uniques":0},{"timestamp":"2025-07-15T01:45:23.242Z","count":0,"uniques":0}]
