[{"timestamp":"2025-08-07T01:46:20.502Z","count":0,"uniques":0},{"timestamp":"2025-08-08T01:45:57.382Z","count":0,"uniques":0},{"timestamp":"2025-08-09T01:28:38.942Z","count":0,"uniques":0},{"timestamp":"2025-08-10T01:49:29.792Z","count":0,"uniques":0},{"timestamp":"2025-08-11T01:46:25.581Z","count":0,"uniques":0},{"timestamp":"2025-08-12T01:27:54.615Z","count":0,"uniques":0},{"timestamp":"2025-08-13T01:29:22.302Z","count":0,"uniques":0},{"timestamp":"2025-08-14T01:38:52.615Z","count":0,"uniques":0}]
