[{"timestamp":"2025-04-24T01:23:57.052Z","count":0,"uniques":0},{"timestamp":"2025-04-25T01:24:40.170Z","count":0,"uniques":0},{"timestamp":"2025-04-26T01:21:27.974Z","count":0,"uniques":0},{"timestamp":"2025-04-27T01:28:46.631Z","count":0,"uniques":0},{"timestamp":"2025-04-28T01:26:13.896Z","count":0,"uniques":0},{"timestamp":"2025-04-29T01:24:35.346Z","count":0,"uniques":0},{"timestamp":"2025-04-30T01:24:32.408Z","count":0,"uniques":0},{"timestamp":"2025-05-01T01:39:59.603Z","count":0,"uniques":0},{"timestamp":"2025-05-02T01:24:46.178Z","count":0,"uniques":0},{"timestamp":"2025-05-03T01:23:00.031Z","count":0,"uniques":0},{"timestamp":"2025-05-04T01:40:27.825Z","count":0,"uniques":0},{"timestamp":"2025-05-05T01:28:04.874Z","count":0,"uniques":0},{"timestamp":"2025-05-06T01:25:19.458Z","count":0,"uniques":0},{"timestamp":"2025-05-07T01:26:15.618Z","count":0,"uniques":0},{"timestamp":"2025-05-08T01:26:16.568Z","count":0,"uniques":0},{"timestamp":"2025-05-09T01:25:38.462Z","count":0,"uniques":0},{"timestamp":"2025-05-10T01:22:58.596Z","count":0,"uniques":0},{"timestamp":"2025-05-11T01:38:36.243Z","count":0,"uniques":0},{"timestamp":"2025-05-12T01:29:03.990Z","count":0,"uniques":0},{"timestamp":"2025-05-13T01:27:19.078Z","count":0,"uniques":0},{"timestamp":"2025-05-14T01:25:44.898Z","count":0,"uniques":0},{"timestamp":"2025-05-15T01:24:00.531Z","count":0,"uniques":0},{"timestamp":"2025-05-16T01:27:14.910Z","count":0,"uniques":0},{"timestamp":"2025-05-17T01:24:58.676Z","count":0,"uniques":0},{"timestamp":"2025-05-18T01:39:37.534Z","count":0,"uniques":0},{"timestamp":"2025-05-19T01:39:09.724Z","count":0,"uniques":0},{"timestamp":"2025-05-20T01:27:40.502Z","count":0,"uniques":0},{"timestamp":"2025-05-21T01:27:23.197Z","count":0,"uniques":0},{"timestamp":"2025-05-22T01:26:41.329Z","count":0,"uniques":0},{"timestamp":"2025-05-23T01:26:47.293Z","count":0,"uniques":0},{"timestamp":"2025-05-24T01:24:04.751Z","count":0,"uniques":0}]
