[{"timestamp":"2026-02-16T02:06:47.629Z","count":0,"uniques":0},{"timestamp":"2026-02-17T02:04:11.088Z","count":0,"uniques":0},{"timestamp":"2026-02-18T02:07:56.768Z","count":0,"uniques":0},{"timestamp":"2026-02-19T02:06:46.639Z","count":0,"uniques":0},{"timestamp":"2026-02-20T02:02:45.419Z","count":0,"uniques":0},{"timestamp":"2026-02-21T01:57:26.394Z","count":0,"uniques":0},{"timestamp":"2026-02-22T02:06:37.618Z","count":0,"uniques":0},{"timestamp":"2026-02-23T02:07:21.573Z","count":0,"uniques":0}]
