[{"timestamp":"2025-10-12T01:24:35.519Z","count":0,"uniques":0},{"timestamp":"2025-10-13T01:26:01.451Z","count":0,"uniques":0},{"timestamp":"2025-10-14T01:21:03.779Z","count":0,"uniques":0},{"timestamp":"2025-10-15T01:22:59.040Z","count":0,"uniques":0},{"timestamp":"2025-10-16T01:22:29.511Z","count":0,"uniques":0},{"timestamp":"2025-10-17T01:22:31.507Z","count":0,"uniques":0},{"timestamp":"2025-10-18T01:18:41.531Z","count":0,"uniques":0},{"timestamp":"2025-10-19T01:38:50.041Z","count":0,"uniques":0}]
