[{"timestamp":"2026-02-26T02:08:09.451Z","count":0,"uniques":0},{"timestamp":"2026-02-27T02:07:41.057Z","count":0,"uniques":0},{"timestamp":"2026-02-28T01:57:24.822Z","count":0,"uniques":0},{"timestamp":"2026-03-01T02:20:03.889Z","count":0,"uniques":0},{"timestamp":"2026-03-02T02:10:33.237Z","count":0,"uniques":0},{"timestamp":"2026-03-03T02:11:59.293Z","count":0,"uniques":0},{"timestamp":"2026-03-04T06:52:57.916Z","count":0,"uniques":0},{"timestamp":"2026-03-05T02:09:38.163Z","count":0,"uniques":0}]
