[{"timestamp":"2025-09-30T01:28:14.406Z","count":0,"uniques":0},{"timestamp":"2025-10-01T01:35:48.974Z","count":0,"uniques":0},{"timestamp":"2025-10-02T01:25:35.936Z","count":0,"uniques":0},{"timestamp":"2025-10-03T01:25:23.194Z","count":0,"uniques":0},{"timestamp":"2025-10-04T01:23:22.195Z","count":0,"uniques":0},{"timestamp":"2025-10-05T01:33:29.263Z","count":0,"uniques":0},{"timestamp":"2025-10-06T01:28:21.375Z","count":0,"uniques":0},{"timestamp":"2025-10-07T01:26:28.106Z","count":0,"uniques":0}]
