[{"timestamp":"2025-04-01T13:10:54.374Z","count":0,"uniques":0},{"timestamp":"2025-04-02T13:10:54.374Z","count":0,"uniques":0},{"timestamp":"2025-04-03T13:10:54.374Z","count":0,"uniques":0},{"timestamp":"2025-04-04T01:24:12.107Z","count":0,"uniques":0},{"timestamp":"2025-04-05T01:23:02.522Z","count":0,"uniques":0},{"timestamp":"2025-04-06T01:28:58.832Z","count":0,"uniques":0},{"timestamp":"2025-04-07T00:00:00.000Z","count":1,"uniques":1},{"timestamp":"2025-04-08T00:06:31.141Z","count":0,"uniques":0}]
