[{"timestamp":"2026-06-30T03:37:36.859Z","count":0,"uniques":0},{"timestamp":"2026-07-01T03:46:56.068Z","count":0,"uniques":0},{"timestamp":"2026-07-02T03:32:56.773Z","count":0,"uniques":0},{"timestamp":"2026-07-03T02:56:04.145Z","count":0,"uniques":0},{"timestamp":"2026-07-04T00:00:00.000Z","count":5,"uniques":2},{"timestamp":"2026-07-05T00:00:00.000Z","count":3,"uniques":2},{"timestamp":"2026-07-06T00:00:00.000Z","count":1,"uniques":1},{"timestamp":"2026-07-07T03:02:21.585Z","count":0,"uniques":0}]
