[{"timestamp":"2026-02-22T02:09:09.836Z","count":0,"uniques":0},{"timestamp":"2026-02-23T02:09:47.001Z","count":0,"uniques":0},{"timestamp":"2026-02-24T02:06:23.928Z","count":0,"uniques":0},{"timestamp":"2026-02-25T02:08:45.979Z","count":0,"uniques":0},{"timestamp":"2026-02-26T02:04:31.339Z","count":0,"uniques":0},{"timestamp":"2026-02-27T02:03:53.436Z","count":0,"uniques":0},{"timestamp":"2026-02-28T01:53:53.895Z","count":0,"uniques":0},{"timestamp":"2026-03-01T02:16:14.136Z","count":0,"uniques":0}]
